holmanctl.py
holman/__init__.py
holman/holman.py
holman-0.1.0.dist-info/DESCRIPTION.rst
holman-0.1.0.dist-info/METADATA
holman-0.1.0.dist-info/RECORD
holman-0.1.0.dist-info/WHEEL
holman-0.1.0.dist-info/entry_points.txt
holman-0.1.0.dist-info/metadata.json
holman-0.1.0.dist-info/top_level.txt
