Metadata-Version: 2.0
Name: holman
Version: 0.1.0
Summary: Holman SDK for Python on Linux
Home-page: https://github.com/scottmckenzie/holman-linux-python
Author: Scott McKenzie
Author-email: developers@noizyland.net
License: MIT
Download-URL: https://github.com/scottmckenzie/holman-linux-python/archive/0.1.0.tar.gz
Keywords: holman
Platform: UNKNOWN
Requires-Dist: gatt (>=0.2.7)
